<?xml version="1.0" encoding="UTF-8" standalone="yes"?>
<sst xmlns="http://schemas.openxmlformats.org/spreadsheetml/2006/main" count="55" uniqueCount="51">
  <si>
    <t>Value</t>
  </si>
  <si>
    <t>Config</t>
  </si>
  <si>
    <t>Key</t>
  </si>
  <si>
    <t>StateFilePath</t>
  </si>
  <si>
    <t>StateTableName</t>
  </si>
  <si>
    <t>EventsFilePath</t>
  </si>
  <si>
    <t>EventsTableName</t>
  </si>
  <si>
    <t>.\TESTS\GetReferences\PeopleState.xlsx</t>
  </si>
  <si>
    <t>.\TESTS\GetReferences\PeopleEvents.xlsx</t>
  </si>
  <si>
    <t>TableState</t>
  </si>
  <si>
    <t>TableEvents</t>
  </si>
  <si>
    <t>PersonFIO</t>
  </si>
  <si>
    <t>Ivanov Ivan Ivanovich</t>
  </si>
  <si>
    <t>SortField.Events</t>
  </si>
  <si>
    <t>Events.RecordNo</t>
  </si>
  <si>
    <t>Model.State.Fields</t>
  </si>
  <si>
    <t>Model.State.Key</t>
  </si>
  <si>
    <t>state_FIO; state_BirthDate; state_City; state_Phone</t>
  </si>
  <si>
    <t>state_FIO</t>
  </si>
  <si>
    <t>Model.Events.Fields</t>
  </si>
  <si>
    <t>Model.Events.Key</t>
  </si>
  <si>
    <t>events_FIO</t>
  </si>
  <si>
    <t>Model.Events.Sort</t>
  </si>
  <si>
    <t>events_RecordNo</t>
  </si>
  <si>
    <t>Map.state_FIO</t>
  </si>
  <si>
    <t>Map.state_BirthDate</t>
  </si>
  <si>
    <t>Map.events_RecordNo</t>
  </si>
  <si>
    <t>Map.events_EventDate</t>
  </si>
  <si>
    <t>events_RecordNo; events_EventDate; events_EventType; events_Department; events_Position; events_Salary</t>
  </si>
  <si>
    <t>Map.state_City</t>
  </si>
  <si>
    <t>Map.state_Phone</t>
  </si>
  <si>
    <t>Map.events_FIO</t>
  </si>
  <si>
    <t>Map.events_EventType</t>
  </si>
  <si>
    <t>Map.events_Department</t>
  </si>
  <si>
    <t>Map.events_Position</t>
  </si>
  <si>
    <t>Map.events_Salary</t>
  </si>
  <si>
    <t>Ключ</t>
  </si>
  <si>
    <t>Алиасы колонок</t>
  </si>
  <si>
    <t>Связвание алиасов с реальными названиями колонок:</t>
  </si>
  <si>
    <t>State Table</t>
  </si>
  <si>
    <t>Events Table</t>
  </si>
  <si>
    <t>FIO|ФИО</t>
  </si>
  <si>
    <t>BirthDate|Дата рождения</t>
  </si>
  <si>
    <t>City|Город</t>
  </si>
  <si>
    <t>Phone|Телефон</t>
  </si>
  <si>
    <t>RecordNo|№</t>
  </si>
  <si>
    <t>EventDate|Дата</t>
  </si>
  <si>
    <t>EventType|Событие</t>
  </si>
  <si>
    <t>Department|Отдел</t>
  </si>
  <si>
    <t>Position|Должность</t>
  </si>
  <si>
    <t>Salary|Оклад</t>
  </si>
</sst>
